{
  "name": "bicycle_parts",
  "row_count": 5401,
  "columns": {
    "price": {
      "type": "float",
      "min": 415.57,
      "max": 1695.74,
      "median": 1556.31
    },
    "weight_g": {
      "type": "int",
      "min": 436,
      "max": 4120,
      "median": 3832
    },
    "category": {
      "type": "categorical",
      "values": [
        "Brakes",
        "Drivetrain",
        "Fork",
        "Frame",
        "Handlebars",
        "Pedals",
        "Saddle"
      ]
    },
    "material": {
      "type": "categorical",
      "values": [
        "Aluminum",
        "Carbon",
        "Steel",
        "Titanium"
      ]
    },
    "brand": {
      "type": "categorical",
      "values": [
        "Campagnolo",
        "Chris King",
        "Continental",
        "DT Swiss",
        "Mavic",
        "SRAM",
        "Shimano"
      ]
    },
    "bike_type": {
      "type": "categorical",
      "values": [
        "Hybrid",
        "Mountain",
        "Road"
      ]
    },
    "is_tubeless_compatible": {
      "type": "bool"
    },
    "condition": {
      "type": "categorical",
      "values": [
        "Like New",
        "New",
        "Used"
      ]
    },
    "warranty_years": {
      "type": "int",
      "min": 3,
      "max": 10,
      "median": 6
    }
  }
}