{
  "name": "solar_panels",
  "row_count": 296,
  "columns": {
    "price": {
      "type": "float",
      "min": 1263.22,
      "max": 4019.22,
      "median": 1359.55
    },
    "wattage": {
      "type": "int",
      "min": 159,
      "max": 539,
      "median": 202
    },
    "efficiency_percent": {
      "type": "float",
      "min": 16.61,
      "max": 23.84,
      "median": 22.61
    },
    "panel_type": {
      "type": "categorical",
      "values": [
        "Bifacial",
        "Monocrystalline",
        "Polycrystalline",
        "Thin-Film"
      ]
    },
    "weight_kg": {
      "type": "float",
      "min": 12.65,
      "max": 29.78,
      "median": 22.22
    },
    "warranty_years": {
      "type": "int",
      "min": 15,
      "max": 25,
      "median": 20
    },
    "degradation_rate": {
      "type": "float",
      "min": 0.23,
      "max": 0.76,
      "median": 0.27
    }
  }
}